README.md
README.rst
setup.py
qqwry/__init__.py
qqwry/cz88update.py
qqwry/py.typed
qqwry/qqwry.py
qqwry_py3.egg-info/PKG-INFO
qqwry_py3.egg-info/SOURCES.txt
qqwry_py3.egg-info/dependency_links.txt
qqwry_py3.egg-info/top_level.txt