Metadata-Version: 2.1
Name: qqwry-py3
Version: 1.2.1
Summary: Lookup location of IP in qqwry.dat, for Python 3.0+
Home-page: https://github.com/animalize/qqwry-python3
Author: Ma Lin
Author-email: malincns@163.com
License: BSD
Keywords: qqwry cz88 纯真 ip归属地
Platform: any
Classifier: Development Status :: 5 - Production/Stable
Classifier: Intended Audience :: Developers
Classifier: License :: OSI Approved :: BSD License
Classifier: Operating System :: OS Independent
Classifier: Programming Language :: Python :: 3
Classifier: Programming Language :: Python :: 3 :: Only
Classifier: Topic :: Utilities
